{
  "_class": "shapeGroup",
  "booleanOperation": -1,
  "clippingMaskMode": 0,
  "do_objectID": "2C37F166-5D8D-4868-B64A-12CEB6609F6D",
  "exportOptions": {
    "_class": "exportOptions",
    "do_objectID": "B08FA5BB-4059-45E5-9611-E12E3027795D",
    "exportFormats": [
    ],
    "includedLayerIds": [
    ],
    "layerOptions": 0,
    "shouldTrim": false
  },
  "frame": {
    "_class": "rect",
    "constrainProportions": false,
    "do_objectID": "57FD37A5-2A42-485A-8438-EBE4FDDD6C52",
    "height": 122,
    "width": 1024,
    "x": 0,
    "y": 1205
  },
  "hasClickThrough": false,
  "hasClippingMask": false,
  "isFixedToViewport": false,
  "isFlippedHorizontal": false,
  "isFlippedVertical": false,
  "isLocked": false,
  "isVisible": true,
  "layerListExpandedType": 0,
  "layers": [
    {
      "class": "rectangle",
      "id": "A9447014-71BB-4FE9-BC9F-C5488AE5915D"
    }
  ],
  "name": "Rectangle",
  "nameIsFixed": false,
  "resizingConstraint": 63,
  "resizingType": 0,
  "rotation": 0,
  "shouldBreakMaskChain": false,
  "style": {
    "_class": "style",
    "borders": [
      {
        "_class": "border",
        "color": {
          "_class": "color",
          "alpha": 1,
          "blue": 0.592,
          "green": 0.592,
          "red": 0.592
        },
        "fillType": 0,
        "isEnabled": false,
        "position": 1,
        "thickness": 1
      }
    ],
    "do_objectID": "6DC0A59A-A641-42FB-BC49-E4E10E60976E",
    "endMarkerType": 0,
    "fills": [
      {
        "_class": "fill",
        "color": {
          "_class": "color",
          "alpha": 1,
          "blue": 0.847,
          "green": 0.847,
          "red": 0.847
        },
        "fillType": 4,
        "image": {
          "_class": "MSJSONFileReference",
          "_ref": "images/38f0ead8d0c0780049b02cfa94b5edeb4754a2f4.png",
          "_ref_class": "MSImageData"
        },
        "isEnabled": true,
        "noiseIndex": 0,
        "noiseIntensity": 0,
        "patternFillType": 1,
        "patternTileScale": 0.4396446078431372
      }
    ],
    "miterLimit": 10,
    "shadows": [
      {
        "_class": "shadow",
        "blurRadius": 5,
        "color": {
          "_class": "color",
          "alpha": 0.2581804800724637,
          "blue": 0,
          "green": 0,
          "red": 0
        },
        "contextSettings": {
          "_class": "graphicsContextSettings",
          "blendMode": 0,
          "opacity": 1
        },
        "isEnabled": true,
        "offsetX": 0,
        "offsetY": -3,
        "spread": 2
      }
    ],
    "startMarkerType": 0,
    "windingRule": 0
  },
  "windingRule": 0
}